clipman/__init__.py
clipman/__version__.py
clipman/exceptions.py
clipman/kde.py
clipman/windows.py
clipman-3.3.3.dist-info/licenses/LICENSE
clipman-3.3.3.dist-info/METADATA
clipman-3.3.3.dist-info/WHEEL
clipman-3.3.3.dist-info/top_level.txt
clipman-3.3.3.dist-info/RECORD
