Metadata-Version: 2.4
Name: clipman
Version: 3.3.3
Summary: Python3 module for working with clipboard. Created because pyperclip is discontinued.
Author-email: NikitaBeloglazov <nnikita.beloglazov@gmail.com>
License: MPL 2.0 License
Project-URL: Homepage, https://github.com/NikitaBeloglazov/clipman
Project-URL: Bug Tracker, https://github.com/NikitaBeloglazov/clipman/issues
Keywords: clipman,clipboard,copy,paste,xclip
Classifier: Programming Language :: Python :: 3
Classifier: Development Status :: 5 - Production/Stable
Classifier: Intended Audience :: Developers
Classifier: Topic :: Software Development :: Libraries :: Python Modules
Classifier: License :: OSI Approved :: Mozilla Public License 2.0 (MPL 2.0)
Requires-Python: >=3.9
License-File: LICENSE
Requires-Dist: dbus_next
Dynamic: license-file
